{"/etc/issue.net":"Ubuntu 24.04.4 LTS","antiFeatures":{},"apksigner":"/usr/local/lib/android/sdk/build-tools/37.0.0/apksigner","archivePolicy0":[],"commandLine":["/home/runner/.local/bin/fdroid update","--verbose"],"disabled":[],"endTimestamp":1777882427819,"failedBuilds":{"com.northstarlabs.fantag":[1]},"fdroiddata":{"commitId":"3e04ad01e5236873fd3e040ec6f1f89b5731a6cb","isDirty":false,"modifiedFiles":[],"untrackedFiles":[]},"jarsigner":"/usr/bin/jarsigner","keytool":"/usr/bin/keytool","needsUpdate":["c09c370f84aca9c7556325af097998869942369159bf2182dfc87cda54cb8385","com.northstarlabs.fantag","com.northstarworks.streamvault.tv","com.northstarworks.streamvault","com.northstarworks.svconfig"],"noPackages":["c09c370f84aca9c7556325af097998869942369159bf2182dfc87cda54cb8385","com.northstarlabs.fantag","com.northstarworks.advancedflashcards","com.northstarworks.streamvault.tv","com.northstarworks.streamvault","com.northstarworks.svconfig","com.sidscri.svconfig"],"noUpdateCheck":["c09c370f84aca9c7556325af097998869942369159bf2182dfc87cda54cb8385","com.northstarlabs.fantag","com.northstarworks.advancedflashcards","com.northstarworks.streamvault.tv","com.northstarworks.streamvault","com.northstarworks.svconfig","com.sidscri.svconfig"],"stages":{"archive_old_apks archive":1777882420603,"delete_disabled_builds":1777882417714,"index.make archive":1777882420605,"index.make repo":1777882424777,"prepare_apps archive":1777882420605,"prepare_apps repo":1777882424775,"process_apks":1777882417714,"read_added_date_from_all_apks":1777882420602,"remove_apks":1777882420601,"scan_repo_files":1777882420600},"startTimestamp":1777882417000,"subcommand":"update"}