{"/etc/issue.net":"Ubuntu 24.04.4 LTS","antiFeatures":{},"apksigner":"/usr/local/lib/android/sdk/build-tools/37.0.0/apksigner","archivePolicy0":[],"commandLine":["/home/runner/.local/bin/fdroid update","--verbose"],"disabled":[],"endTimestamp":1778090405572,"failedBuilds":{"com.northstarlabs.fantag":[1]},"fdroiddata":{"commitId":"38e3b2fcb12fb9869e737bd132e3993a8c9d018e","isDirty":false,"modifiedFiles":[],"untrackedFiles":[]},"jarsigner":"/usr/bin/jarsigner","keytool":"/usr/bin/keytool","needsUpdate":["c09c370f84aca9c7556325af097998869942369159bf2182dfc87cda54cb8385","com.northstarlabs.fantag","com.northstarworks.streamvault.tv","com.northstarworks.streamvault","com.northstarworks.svconfig"],"noPackages":["c09c370f84aca9c7556325af097998869942369159bf2182dfc87cda54cb8385","com.northstarlabs.fantag","com.northstarworks.advancedflashcards","com.northstarworks.streamvault.tv","com.northstarworks.streamvault","com.northstarworks.svconfig","com.sidscri.svconfig"],"noUpdateCheck":["c09c370f84aca9c7556325af097998869942369159bf2182dfc87cda54cb8385","com.northstarlabs.fantag","com.northstarworks.advancedflashcards","com.northstarworks.streamvault.tv","com.northstarworks.streamvault","com.northstarworks.svconfig","com.sidscri.svconfig"],"stages":{"archive_old_apks archive":1778090398960,"delete_disabled_builds":1778090397364,"index.make archive":1778090398962,"index.make repo":1778090402526,"prepare_apps archive":1778090398961,"prepare_apps repo":1778090402524,"process_apks":1778090397364,"read_added_date_from_all_apks":1778090398960,"remove_apks":1778090398958,"scan_repo_files":1778090398957},"startTimestamp":1778090396000,"subcommand":"update"}